megamind_sdk/setup.py
megamind_sdk/api/__init__.py
megamind_sdk/api/progress_report.py
megamind_sdk/api/training_master_client.py
megamind_sdk/utils/__init__.py
megamind_sdk/utils/std_stream_proxy.py
megamind_sdk-1.0.0.post2.dist-info/METADATA
megamind_sdk-1.0.0.post2.dist-info/WHEEL
megamind_sdk-1.0.0.post2.dist-info/top_level.txt
megamind_sdk-1.0.0.post2.dist-info/RECORD
